edwh_pipcompile_plugin/__about__.py
edwh_pipcompile_plugin/__init__.py
edwh_pipcompile_plugin/pipcompile_plugin.py
edwh_pipcompile_plugin-0.6.1.dist-info/METADATA
edwh_pipcompile_plugin-0.6.1.dist-info/WHEEL
edwh_pipcompile_plugin-0.6.1.dist-info/entry_points.txt
edwh_pipcompile_plugin-0.6.1.dist-info/licenses/LICENSE.txt
edwh_pipcompile_plugin-0.6.1.dist-info/RECORD
