Metadata-Version: 2.4
Name: edwh-pipcompile-plugin
Version: 0.6.1
Summary: Plugin that integrates `pip-tools` with `edwh`
Project-URL: Documentation, https://github.com/educationwarehouse/edwh-pipcompile-plugin#readme
Project-URL: Issues, https://github.com/educationwarehouse/edwh-pipcompile-plugin/issues
Project-URL: Source, https://github.com/educationwarehouse/edwh-pipcompile-plugin
Author-email: Robin van der Noord <robin.vdn@educationwarehouse.nl>, Remco Boerma <remco.b@educationwarehouse.nl>
License-Expression: MIT
License-File: LICENSE.txt
Classifier: Development Status :: 4 - Beta
Classifier: Programming Language :: Python
Classifier: Programming Language :: Python :: 3.10
Classifier: Programming Language :: Python :: 3.11
Classifier: Programming Language :: Python :: 3.12
Classifier: Programming Language :: Python :: Implementation :: CPython
Classifier: Programming Language :: Python :: Implementation :: PyPy
Requires-Python: >=3.10
Requires-Dist: edwh>=0.19
Requires-Dist: tomli
Requires-Dist: typing-extensions
Requires-Dist: uv
Provides-Extra: dev
Requires-Dist: black; extra == 'dev'
Requires-Dist: edwh; extra == 'dev'
Requires-Dist: hatch; extra == 'dev'
